LICENSE
MANIFEST.in
README.md
VERSION
setup.py
granoloader/__init__.py
granoloader/command.py
granoloader/mapping.py
granoloader.egg-info/PKG-INFO
granoloader.egg-info/SOURCES.txt
granoloader.egg-info/dependency_links.txt
granoloader.egg-info/entry_points.txt
granoloader.egg-info/not-zip-safe
granoloader.egg-info/requires.txt
granoloader.egg-info/top_level.txt